PenikmatDoujin/__init__.py
PenikmatDoujin/main.py
PenikmatDoujin/Module/__init__.py
PenikmatDoujin/Module/cbz.py
PenikmatDoujin/Module/checkfolder.py
PenikmatDoujin/Module/chnumber.py
PenikmatDoujin/Module/dataclass.py
PenikmatDoujin/Module/dl.py
PenikmatDoujin/Module/parseURL.py
PenikmatDoujin/Module/test.py
PenikmatDoujin/Module/webp.py
PenikmatDoujin/Module/SiteParser/Manhwa18.py
PenikmatDoujin/Module/SiteParser/__init__.py
PenikmatDoujin/Module/SiteParser/dojing.py
PenikmatDoujin/Module/SiteParser/fastmanhwa.py
PenikmatDoujin/Module/SiteParser/komiklokal.py
PenikmatDoujin/Module/SiteParser/kumapoi.py
PenikmatDoujin/Module/SiteParser/manytoon.py
PenikmatDoujin/Module/SiteParser/qinimg.py
PenikmatDoujin/Module/SiteParser/sektedoujin.py
PenikmatDoujin/Module/SiteParser/worldmanhwas.py
penikmatdoujin-1.2.dist-info/METADATA
penikmatdoujin-1.2.dist-info/WHEEL
penikmatdoujin-1.2.dist-info/entry_points.txt
penikmatdoujin-1.2.dist-info/top_level.txt
penikmatdoujin-1.2.dist-info/RECORD
