Metadata-Version: 2.1
Name: penikmatdoujin
Version: 1.2
Summary: Doujin Downlaoder
Author: AriKu
Author-email: noobhek@gmail.com
Keywords: python,manga,manga-downloader
Classifier: Programming Language :: Python :: 3
Classifier: Operating System :: Unix
Classifier: Operating System :: Microsoft :: Windows
Requires-Dist: tqdm
Requires-Dist: urllib3
Requires-Dist: bs4
